wscrap/__init__.py
wscrap/__main__.py
wscrap/utils.py
wscrap-0.1.0.dist-info/entry_points.txt
wscrap-0.1.0.dist-info/WHEEL
wscrap-0.1.0.dist-info/METADATA
wscrap-0.1.0.dist-info/RECORD
